api/__init__.py
api/__main__.py
api-0.0.1.dev1.dist-info/DESCRIPTION.rst
api-0.0.1.dev1.dist-info/METADATA
api-0.0.1.dev1.dist-info/RECORD
api-0.0.1.dev1.dist-info/WHEEL
api-0.0.1.dev1.dist-info/metadata.json
api-0.0.1.dev1.dist-info/pbr.json
api-0.0.1.dev1.dist-info/top_level.txt
