Metadata-Version: 2.0
Name: api
Version: 0.0.1.dev1
Summary: Api lib for simple life
Home-page: http://pypi.python.org/pypi/api
Author: Rain
Author-email: 1044908508@qq.com
License: MIT
Platform: UNKNOWN
Classifier: Development Status :: 4 - Beta
Classifier: Environment :: Console
Classifier: Intended Audience :: Developers
Classifier: Intended Audience :: Information Technology
Classifier: Natural Language :: English
Requires-Dist: requests (==2.12.1)
